dahlia/__init__.py
dahlia/__main__.py
dahlia/constants.py
dahlia/lib.py
dahlia/py.typed
dahlia/utils.py
dahlia-3.1.0.dist-info/METADATA
dahlia-3.1.0.dist-info/WHEEL
dahlia-3.1.0.dist-info/licenses/LICENSE
dahlia-3.1.0.dist-info/RECORD
