Metadata-Version: 2.4
Name: dahlia
Version: 3.1.0
Summary: A library allowing you to use Minecraft format codes in strings.
Author-email: trag1c <trag1cdev@yahoo.com>
License: MIT License
License-File: LICENSE
Requires-Python: >=3.9
